geoprisma
