Metadata-Version: 1.1
Name: django-geoprisma
Version: 0.0.1
Summary: GeoPrisma is a web mapping application
Home-page: https://github.com/groupe-conseil-nutshimit-nippour/django-geoprisma
Author: Groupe Conseil Nutshimit-Nippour
Author-email: geoprisma@gcnn.ca
License: BSD License
Platform: UNKNOWN
Classifier: Environment :: Web Environment
Classifier: Framework :: Django
Classifier: Intended Audience :: Developers
Classifier: License :: OSI Approved :: BSD License
Classifier: Operating System :: OS Independent
Classifier: Programming Language :: Python
Classifier: Topic :: Internet :: WWW/HTTP
Classifier: Topic :: Software Development :: Libraries :: Python Modules
